limiter/__init__.py
limiter/clients.py
limiter/event_processors.py
limiter/exceptions.py
limiter/limiters.py
limiter/loader.py
limiter/managers.py
limiter/utils.py
test/__init__.py
test/test_event_processors.py
test/test_limiters.py
test/test_managers.py
test/utils.py
rate_limiter_modern_py-0.4.0.dist-info/METADATA
rate_limiter_modern_py-0.4.0.dist-info/WHEEL
rate_limiter_modern_py-0.4.0.dist-info/top_level.txt
rate_limiter_modern_py-0.4.0.dist-info/RECORD
